core/__init__.py
core/analyseur.py
core/simulateur.py
exceptions/__init__.py
exceptions/exceptions.py
inout/__init__.py
inout/affichage.py
inout/export.py
inout/setup.py
models/__init__.py
models/reseau.py
models/route.py
models/vehicule.py
simulateur_trafic_package-0.1.0.dist-info/METADATA
simulateur_trafic_package-0.1.0.dist-info/WHEEL
simulateur_trafic_package-0.1.0.dist-info/top_level.txt
simulateur_trafic_package-0.1.0.dist-info/RECORD
