Metadata-Version: 2.4
Name: simulateur_trafic_package
Version: 0.1.0
Summary: Un simulateur modulaire du trafic routier permettant de modéliser des routes, intersections et véhicules, et de visualiser les résultats de simulation sous forme graphique.
Author: Amaidi Chaima
Author-email: amaidiamaidi13@gmail.com
Classifier: Programming Language :: Python :: 3.8
Requires-Python: >=3.8
Requires-Dist: matplotlib>=3.7.1
Requires-Dist: numpy>=1.26.0
Requires-Dist: numba>=0.58.0
Dynamic: author
Dynamic: author-email
Dynamic: classifier
Dynamic: description
Dynamic: description-content-type
Dynamic: requires-dist
Dynamic: requires-python
Dynamic: summary
